vvs_portal_gun/__init__.py
vvs_portal_gun/__main__.py
vvs_portal_gun/main.py
vvs_portal_gun-0.1.0.dist-info/entry_points.txt
vvs_portal_gun-0.1.0.dist-info/WHEEL
vvs_portal_gun-0.1.0.dist-info/METADATA
vvs_portal_gun-0.1.0.dist-info/RECORD
