Metadata-Version: 2.1
Name: vvs-portal-gun
Version: 0.1.0
Summary: 
Author: Vikash_Vikram
Author-email: Vikash_Vikram@external.mckinsey.com
Requires-Python: >=3.9,<4.0
Classifier: Programming Language :: Python :: 3
Classifier: Programming Language :: Python :: 3.9
Requires-Dist: typer[all] (>=0.3.2,<0.4.0)
